{"autoTags":[{"value":"bike","confidence":0.7509706020355225,"isCustom":false},{"value":"bicycle","confidence":0.7354774475097656,"isCustom":false},{"value":"wheel","confidence":0.6410011649131775,"isCustom":false},{"value":"city","confidence":0.6198214292526245,"isCustom":false},{"value":"sport","confidence":0.6048647165298462,"isCustom":false},{"value":"transport","confidence":0.5978348851203918,"isCustom":false},{"value":"cycle","confidence":0.5883264541625977,"isCustom":false},{"value":"street","confidence":0.5836145877838135,"isCustom":false},{"value":"ride","confidence":0.5723828077316284,"isCustom":false},{"value":"man","confidence":0.5721613764762878,"isCustom":false},{"value":"road","confidence":0.55814528465271,"isCustom":false},{"value":"travel","confidence":0.5569796562194824,"isCustom":false},{"value":"cycling","confidence":0.5560965538024902,"isCustom":false},{"value":"urban","confidence":0.5558876991271973,"isCustom":false},{"value":"people","confidence":0.5381391048431396,"isCustom":false},{"value":"transportation","confidence":0.5201361775398254,"isCustom":false},{"value":"equipment","confidence":0.5195952653884888,"isCustom":false},{"value":"old","confidence":0.5162420272827148,"isCustom":false},{"value":"biking","confidence":0.5154418349266052,"isCustom":false},{"value":"speed","confidence":0.5152220726013184,"isCustom":false},{"value":"biker","confidence":0.511867344379425,"isCustom":false},{"value":"cyclist","confidence":0.5110492706298828,"isCustom":false},{"value":"sports","confidence":0.5048618912696838,"isCustom":false},{"value":"motorcycle","confidence":0.5047594904899597,"isCustom":false}]}
